judoka/__init__.py
judoka/cli.py
judoka/command.py
judoka/completion.py
judoka/config.py
judoka/completions/__init__.py
judoka/completions/judo.bash
judoka/completions/judo.fish
judoka/completions/judo.zsh
judoka-0.3.6.dist-info/LICENSE
judoka-0.3.6.dist-info/METADATA
judoka-0.3.6.dist-info/WHEEL
judoka-0.3.6.dist-info/entry_points.txt
judoka-0.3.6.dist-info/top_level.txt
judoka-0.3.6.dist-info/RECORD
