Metadata-Version: 2.1
Name: judoka
Version: 0.3.6
Summary: UNKNOWN
Home-page: https://github.com/eelkevdbos/judoka
Author: Eelke van den Bos
License: MIT
Project-URL: Issues, https://github.com/eelkevdbos/judoka/issues
Project-URL: CI, https://github.com/eelkevdbos/judoka/actions
Project-URL: Changelog, https://github.com/eelkevdbos/judoka/releases
Platform: UNKNOWN
Requires-Python: >=3.6
License-File: LICENSE
Requires-Dist: toml (~=0.10)
Requires-Dist: click (~=8.0)
Provides-Extra: test
Requires-Dist: pytest ; extra == 'test'
